README.md
setup.py
telegram_bot_sdk/__init__.py
telegram_bot_sdk/config.py
telegram_bot_sdk/main.py
telegram_bot_sdk/telegram.py
telegram_bot_sdk.egg-info/PKG-INFO
telegram_bot_sdk.egg-info/SOURCES.txt
telegram_bot_sdk.egg-info/dependency_links.txt
telegram_bot_sdk.egg-info/requires.txt
telegram_bot_sdk.egg-info/top_level.txt
telegram_bot_sdk/controller/__init__.py
telegram_bot_sdk/controller/controller.py
telegram_bot_sdk/exceptions/__init__.py
telegram_bot_sdk/exceptions/message_exception.py
telegram_bot_sdk/exceptions/web_exception.py
telegram_bot_sdk/helper/__init__.py
telegram_bot_sdk/helper/config_manager.py
telegram_bot_sdk/helper/observer.py
telegram_bot_sdk/helper/travseral.py
telegram_bot_sdk/helper/util.py
telegram_bot_sdk/modules/__init__.py
telegram_bot_sdk/network/__init__.py
telegram_bot_sdk/network/network.py
telegram_bot_sdk/telegram_objects/__init__.py
telegram_bot_sdk/telegram_objects/animation.py
telegram_bot_sdk/telegram_objects/audio.py
telegram_bot_sdk/telegram_objects/callbackGame.py
telegram_bot_sdk/telegram_objects/callbackQuery.py
telegram_bot_sdk/telegram_objects/chat.py
telegram_bot_sdk/telegram_objects/chatMember.py
telegram_bot_sdk/telegram_objects/chatPermissions.py
telegram_bot_sdk/telegram_objects/chatPhoto.py
telegram_bot_sdk/telegram_objects/chosenInlineResult.py
telegram_bot_sdk/telegram_objects/contact.py
telegram_bot_sdk/telegram_objects/document.py
telegram_bot_sdk/telegram_objects/encryptedCredentials.py
telegram_bot_sdk/telegram_objects/encryptedPassportElement.py
telegram_bot_sdk/telegram_objects/file.py
telegram_bot_sdk/telegram_objects/forceReply.py
telegram_bot_sdk/telegram_objects/game.py
telegram_bot_sdk/telegram_objects/inlineKeyboardButton.py
telegram_bot_sdk/telegram_objects/inlineKeyboardMarkup.py
telegram_bot_sdk/telegram_objects/inlineQuery.py
telegram_bot_sdk/telegram_objects/inlineQueryResult.py
telegram_bot_sdk/telegram_objects/inlineQueryResultArticle.py
telegram_bot_sdk/telegram_objects/inlineQueryResultPhoto.py
telegram_bot_sdk/telegram_objects/inputContactMessageContent.py
telegram_bot_sdk/telegram_objects/inputFile.py
telegram_bot_sdk/telegram_objects/inputLocationMessageContent.py
