Metadata-Version: 2.1
Name: telegram-bot-sdk
Version: 0.3.9
Summary: A Implementation of the Telegram Bot API
Home-page: https://github.com/myOmikron/TelegramBotAPI
Author: myOmikron
Author-email: kontakt@omikron.pw
License: UNKNOWN
Platform: UNKNOWN
Classifier: Programming Language :: Python :: 3
Classifier: License :: OSI Approved :: MIT License
Classifier: Operating System :: OS Independent
Requires-Python: >=3.7
